gps_building_blocks/__init__.py
gps_building_blocks/airflow/__init__.py
gps_building_blocks/airflow/hooks/__init__.py
gps_building_blocks/airflow/hooks/automl_tables_hook.py
gps_building_blocks/airflow/hooks/automl_tables_hook_test.py
gps_building_blocks/airflow/hooks/bq_hook.py
gps_building_blocks/airflow/hooks/bq_hook_test.py
gps_building_blocks/airflow/hooks/ga_hook.py
gps_building_blocks/airflow/hooks/ga_hook_test.py
gps_building_blocks/airflow/hooks/gcs_hook.py
gps_building_blocks/airflow/hooks/gcs_hook_test.py
gps_building_blocks/airflow/hooks/input_hook_interface.py
gps_building_blocks/airflow/hooks/output_hook_interface.py
gps_building_blocks/airflow/operators/__init__.py
gps_building_blocks/airflow/operators/automl_tables_batch_prediction_operator.py
gps_building_blocks/airflow/operators/automl_tables_batch_prediction_operator_test.py
gps_building_blocks/airflow/operators/bq_to_ga_operator.py
gps_building_blocks/airflow/operators/bq_to_ga_operator_test.py
gps_building_blocks/airflow/operators/data_connector_operator.py
gps_building_blocks/airflow/operators/data_connector_operator_test.py
gps_building_blocks/airflow/operators/gcs_to_ga_operator.py
gps_building_blocks/airflow/operators/gcs_to_ga_operator_test.py
gps_building_blocks/airflow/utils/__init__.py
gps_building_blocks/airflow/utils/blob.py
gps_building_blocks/airflow/utils/blob_test.py
gps_building_blocks/airflow/utils/errors.py
gps_building_blocks/airflow/utils/errors_test.py
gps_building_blocks/airflow/utils/retry_utils.py
gps_building_blocks/airflow/utils/retry_utils_test.py
gps_building_blocks/analysis/__init__.py
gps_building_blocks/analysis/feature_graph_visualization.py
gps_building_blocks/analysis/feature_graph_visualization_test.py
gps_building_blocks/analysis/exp_design/__init__.py
gps_building_blocks/analysis/exp_design/ab_testing_analysis.py
gps_building_blocks/analysis/exp_design/ab_testing_analysis_test.py
gps_building_blocks/analysis/exp_design/ab_testing_design.py
gps_building_blocks-1.258.0.dist-info/METADATA
gps_building_blocks-1.258.0.dist-info/WHEEL
gps_building_blocks-1.258.0.dist-info/top_level.txt
gps_building_blocks-1.258.0.dist-info/RECORD
