Metadata-Version: 2.4
Name: gps-building-blocks
Version: 1.258.0
Summary: Modules and tools useful for use with advanced data solutions on Google Ads, Google Marketing Platform and Google Cloud.
Home-page: https://github.com/google/gps_building_blocks
Author: gPS Team
Author-email: no-reply@google.com
License: Apache Software License
Classifier: Intended Audience :: Developers
Classifier: Topic :: Software Development :: Libraries :: Python Modules
Classifier: Topic :: Internet
Classifier: Topic :: Scientific/Engineering
Classifier: License :: OSI Approved :: Apache Software License
Classifier: Programming Language :: Python
Classifier: Operating System :: OS Independent
Requires-Dist: absl-py==2.0.0
Requires-Dist: apache-airflow<3.0,>=2.7.2
Requires-Dist: apache-airflow-providers-google<11.0,>=10.10.1
Requires-Dist: google-api-core[grpc]<3.0,>=2.12.0
Requires-Dist: google-api-python-client<3.0,>=2.105.0
Requires-Dist: google-auth<3.0,>=2.23.3
Requires-Dist: google-cloud-bigquery<4.0,>=3.12.0
Requires-Dist: google-cloud-firestore<3.0,>=2.13.0
Requires-Dist: google-cloud-pubsub<3.0,>=2.18.4
Requires-Dist: google-cloud-storage<3.0,>=2.12.0
Requires-Dist: importlib-resources<7.0,>=6.1.0
Requires-Dist: lightgbm==4.1.0
Requires-Dist: matplotlib==3.7.3
Requires-Dist: networkx==3.1
Requires-Dist: numpy<2.0,>=1.24.3
Requires-Dist: pandas<3.0,>=2.0.3
Requires-Dist: pandas-gbq==0.19.2
Requires-Dist: parameterized==0.9.0
Requires-Dist: plotly==5.18.0
Requires-Dist: requests<3.0,>=2.31.0
Requires-Dist: setuptools==66.1.1
Requires-Dist: scikit-learn==1.1.3
Requires-Dist: scipy==1.10.1
Requires-Dist: seaborn==0.12.2
Requires-Dist: sqlparse==0.4.4
Requires-Dist: statsmodels==0.14.0
Requires-Dist: tensorflow==2.13.1
Requires-Dist: tensorflow-hub==0.15.0
Requires-Dist: tensorflow-probability==0.21.0
Dynamic: author
Dynamic: author-email
Dynamic: classifier
Dynamic: description
Dynamic: description-content-type
Dynamic: home-page
Dynamic: license
Dynamic: requires-dist
Dynamic: summary
